odoo/addons/crm_security_group/README.rst
odoo/addons/crm_security_group/__init__.py
odoo/addons/crm_security_group/__manifest__.py
odoo/addons/crm_security_group/i18n/crm_security_group.pot
odoo/addons/crm_security_group/readme/CONTRIBUTORS.rst
odoo/addons/crm_security_group/readme/DESCRIPTION.rst
odoo/addons/crm_security_group/readme/ROADMAP.rst
odoo/addons/crm_security_group/security/ir.model.access.csv
odoo/addons/crm_security_group/security/security.xml
odoo/addons/crm_security_group/static/description/icon.png
odoo/addons/crm_security_group/static/description/index.html
odoo/addons/crm_security_group/tests/__init__.py
odoo/addons/crm_security_group/tests/test_crm_security.py
odoo/addons/crm_security_group/views/menu_items.xml
odoo13_addon_crm_security_group-13.0.1.1.0.dist-info/METADATA
odoo13_addon_crm_security_group-13.0.1.1.0.dist-info/WHEEL
odoo13_addon_crm_security_group-13.0.1.1.0.dist-info/top_level.txt
odoo13_addon_crm_security_group-13.0.1.1.0.dist-info/RECORD
